tfmops/__init__.py
tfmops/ranking.py
tfmops-0.0.0.dist-info/AUTHORS.rst
tfmops-0.0.0.dist-info/LICENSE
tfmops-0.0.0.dist-info/METADATA
tfmops-0.0.0.dist-info/WHEEL
tfmops-0.0.0.dist-info/top_level.txt
tfmops-0.0.0.dist-info/RECORD
